pygua64/__init__.py
pygua64/gua64.py
pygua64-0.0.2.dist-info/LICENSE
pygua64-0.0.2.dist-info/METADATA
pygua64-0.0.2.dist-info/WHEEL
pygua64-0.0.2.dist-info/top_level.txt
pygua64-0.0.2.dist-info/RECORD
