Metadata-Version: 2.1
Name: pygua64
Version: 0.0.2
Summary: 六十四卦编码，python实现。
Home-page: https://github.com/lizongying/pygua64
Author: Li ZongYing
Author-email: lizongying@msn.com
Project-URL: Bug Tracker, https://github.com/lizongying/pygua64/issues
Classifier: Programming Language :: Python :: 3
Classifier: License :: OSI Approved :: MIT License
Classifier: Operating System :: OS Independent
Requires-Python: >=3.6
License-File: LICENSE
